{
  "project_info": {
    "project_number": "600506065348",
    "project_id": "lendsqr-ed2f3",
    "storage_bucket": "lendsqr-ed2f3.appspot.com"
  },
  "client": [
    {
      "client_info": {
        "mobilesdk_app_id": "1:600506065348:android:25d6f03d62a15810058491",
        "android_client_info": {
          "package_name": "com.lendsqr"
        }
      },
      "oauth_client": [
        {
          "client_id": "600506065348-5fp38nm2go1llj8ef44t5ouhoeu0kup8.apps.googleusercontent.com",
          "client_type": 1,
          "android_info": {
            "package_name": "com.lendsqr",
            "certificate_hash": "5e8f16062ea3cd2c4a0d547876baa6f38cabf625"
          }
        },
        {
          "client_id": "600506065348-majapleh3175bplrgihbtu9cfdfborq7.apps.googleusercontent.com",
          "client_type": 3
        }
      ],
      "api_key": [
        {
          "current_key": "AIzaSyA79roY-wYLybf5_1_wbHwbpXpCxESb2CY"
        }
      ],
      "services": {
        "appinvite_service": {
          "other_platform_oauth_client": [
            {
              "client_id": "600506065348-majapleh3175bplrgihbtu9cfdfborq7.apps.googleusercontent.com",
              "client_type": 3
            },
            {
              "client_id": "600506065348-dqdceuk455bpsp33584te9fdojf7c44e.apps.googleusercontent.com",
              "client_type": 2,
              "ios_info": {
                "bundle_id": "org.reactjs.native.example.Lendsqr"
              }
            }
          ]
        }
      }
    }
  ],
  "configuration_version": "1"
}